<?xml version="1.0" encoding="utf-8"?>
<RelayFile>
    <FileHeader>
        <Description>SC;unknown_ver;2018-02-20T07:45:09-05:00</Description>
        <Version>6</Version>
    </FileHeader>
    <FuelingPointRecords>
        <record>
            <FuelingPointNumber>1</FuelingPointNumber>
            <Enabled>1</Enabled>
            <DefaultTier>1</DefaultTier>
            <ServiceMode>1</ServiceMode>
            <VolumeMultiplier>1000</VolumeMultiplier>
            <PricePerUnitMultiplier>1000</PricePerUnitMultiplier>
            <MoneyMultiplier>100</MoneyMultiplier>
            <MaxAuthAmount>20000</MaxAuthAmount>
            <MaxAuthVolume>200000</MaxAuthVolume>
            <CallingAction>0</CallingAction>
            <NonIntegratedPump>0</NonIntegratedPump>
            <PumpPPUPrecision>3</PumpPPUPrecision>
            <PumpMoneyPrecision>2</PumpMoneyPrecision>
            <PumpVolumePrecision>3</PumpVolumePrecision>
            <MaxStack>2</MaxStack>
            <HoseRecords>
                <record>
                    <HoseNumber>1</HoseNumber>
                    <Enabled>1</Enabled>
                    <ProductNumber>70000019</ProductNumber>
                    <PrimaryTank>1</PrimaryTank>
                    <SecondaryTank>0</SecondaryTank>
                    <PrimaryBlendPercentage>100</PrimaryBlendPercentage>
                    <TierServiceModePrices>
                        <record>
                            <UnitPrice>1000</UnitPrice>
                        </record>
                        <record>
                            <UnitPrice>0</UnitPrice>
                        </record>
                        <record>
                            <UnitPrice>1200</UnitPrice>
                        </record>
                        <record>
                            <UnitPrice>0</UnitPrice>
                        </record>
                        <record>
                            <UnitPrice>0</UnitPrice>
                        </record>
                        <record>
                            <UnitPrice>0</UnitPrice>
                        </record>
                        <record>
                            <UnitPrice>0</UnitPrice>
                        </record>
                        <record>
                            <UnitPrice>0</UnitPrice>
                        </record>
                        <record>
                            <UnitPrice>0</UnitPrice>
                        </record>
                        <record>
                            <UnitPrice>0</UnitPrice>
                        </record>
                    </TierServiceModePrices>
                </record>
                <record>
                    <HoseNumber>2</HoseNumber>
                    <Enabled>1</Enabled>
                    <ProductNumber>70000022</ProductNumber>
                    <PrimaryTank>2</PrimaryTank>
                    <SecondaryTank>0</SecondaryTank>
                    <PrimaryBlendPercentage>100</PrimaryBlendPercentage>
                    <TierServiceModePrices>
                        <record>
                            <UnitPrice>2000</UnitPrice>
                        </record>
                        <record>
                            <UnitPrice>0</UnitPrice>
                        </record>
                        <record>
                            <UnitPrice>2200</UnitPrice>
                        </record>
                        <record>
                            <UnitPrice>0</UnitPrice>
                        </record>
                        <record>
                            <UnitPrice>0</UnitPrice>
                        </record>
                        <record>
                            <UnitPrice>0</UnitPrice>
                        </record>
                        <record>
                            <UnitPrice>0</UnitPrice>
                        </record>
                        <record>
                            <UnitPrice>0</UnitPrice>
                        </record>
                        <record>
                            <UnitPrice>0</UnitPrice>
                        </record>
                        <record>
                            <UnitPrice>0</UnitPrice>
                        </record>
                    </TierServiceModePrices>
                </record>
                <record>
                    <HoseNumber>3</HoseNumber>
                    <Enabled>1</Enabled>
                    <ProductNumber>70000020</ProductNumber>
                    <PrimaryTank>3</PrimaryTank>
                    <SecondaryTank>0</SecondaryTank>
                    <PrimaryBlendPercentage>100</PrimaryBlendPercentage>
                    <TierServiceModePrices>
                        <record>
                            <UnitPrice>3000</UnitPrice>
                        </record>
                        <record>
                            <UnitPrice>0</UnitPrice>
                        </record>
                        <record>
                            <UnitPrice>3200</UnitPrice>
                        </record>
                        <record>
                            <UnitPrice>0</UnitPrice>
                        </record>
                        <record>
                            <UnitPrice>0</UnitPrice>
                        </record>
                        <record>
                            <UnitPrice>0</UnitPrice>
                        </record>
                        <record>
                            <UnitPrice>0</UnitPrice>
                        </record>
                        <record>
                            <UnitPrice>0</UnitPrice>
                        </record>
                        <record>
                            <UnitPrice>0</UnitPrice>
                        </record>
                        <record>
                            <UnitPrice>0</UnitPrice>
                        </record>
                    </TierServiceModePrices>
                </record>
                <record>
                    <HoseNumber>4</HoseNumber>
                    <Enabled>1</Enabled>
                    <ProductNumber>70000021</ProductNumber>
                    <PrimaryTank>4</PrimaryTank>
                    <SecondaryTank>0</SecondaryTank>
                    <PrimaryBlendPercentage>100</PrimaryBlendPercentage>
                    <TierServiceModePrices>
                        <record>
                            <UnitPrice>4000</UnitPrice>
                        </record>
                        <record>
                            <UnitPrice>0</UnitPrice>
                        </record>
                        <record>
                            <UnitPrice>4200</UnitPrice>
                        </record>
                        <record>
                            <UnitPrice>0</UnitPrice>
                        </record>
                        <record>
                            <UnitPrice>0</UnitPrice>
                        </record>
                        <record>
                            <UnitPrice>0</UnitPrice>
                        </record>
                        <record>
                            <UnitPrice>0</UnitPrice>
                        </record>
                        <record>
                            <UnitPrice>0</UnitPrice>
                        </record>
                        <record>
                            <UnitPrice>0</UnitPrice>
                        </record>
                        <record>
                            <UnitPrice>0</UnitPrice>
                        </record>
                    </TierServiceModePrices>
                </record>
            </HoseRecords>
        </record>
        <record>
            <FuelingPointNumber>2</FuelingPointNumber>
            <Enabled>1</Enabled>
            <DefaultTier>1</DefaultTier>
            <ServiceMode>1</ServiceMode>
            <VolumeMultiplier>1000</VolumeMultiplier>
            <PricePerUnitMultiplier>1000</PricePerUnitMultiplier>
            <MoneyMultiplier>100</MoneyMultiplier>
            <MaxAuthAmount>20000</MaxAuthAmount>
            <MaxAuthVolume>200000</MaxAuthVolume>
            <CallingAction>0</CallingAction>
            <NonIntegratedPump>0</NonIntegratedPump>
            <PumpPPUPrecision>3</PumpPPUPrecision>
            <PumpMoneyPrecision>2</PumpMoneyPrecision>
            <PumpVolumePrecision>3</PumpVolumePrecision>
            <MaxStack>2</MaxStack>
            <HoseRecords>
                <record>
                    <HoseNumber>1</HoseNumber>
                    <Enabled>1</Enabled>
                    <ProductNumber>70000019</ProductNumber>
                    <PrimaryTank>1</PrimaryTank>
                    <SecondaryTank>0</SecondaryTank>
                    <PrimaryBlendPercentage>100</PrimaryBlendPercentage>
                    <TierServiceModePrices>
                        <record>
                            <UnitPrice>1000</UnitPrice>
                        </record>
                        <record>
                            <UnitPrice>0</UnitPrice>
                        </record>
                        <record>
                            <UnitPrice>1200</UnitPrice>
                        </record>
                        <record>
                            <UnitPrice>0</UnitPrice>
                        </record>
                        <record>
                            <UnitPrice>0</UnitPrice>
                        </record>
                        <record>
                            <UnitPrice>0</UnitPrice>
                        </record>
                        <record>
                            <UnitPrice>0</UnitPrice>
                        </record>
                        <record>
                            <UnitPrice>0</UnitPrice>
                        </record>
                        <record>
                            <UnitPrice>0</UnitPrice>
                        </record>
                        <record>
                            <UnitPrice>0</UnitPrice>
                        </record>
                    </TierServiceModePrices>
                </record>
                <record>
                    <HoseNumber>2</HoseNumber>
                    <Enabled>1</Enabled>
                    <ProductNumber>70000022</ProductNumber>
                    <PrimaryTank>2</PrimaryTank>
                    <SecondaryTank>0</SecondaryTank>
                    <PrimaryBlendPercentage>100</PrimaryBlendPercentage>
                    <TierServiceModePrices>
                        <record>
                            <UnitPrice>2000</UnitPrice>
                        </record>
                        <record>
                            <UnitPrice>0</UnitPrice>
                        </record>
                        <record>
                            <UnitPrice>2200</UnitPrice>
                        </record>
                        <record>
                            <UnitPrice>0</UnitPrice>
                        </record>
                        <record>
                            <UnitPrice>0</UnitPrice>
                        </record>
                        <record>
                            <UnitPrice>0</UnitPrice>
                        </record>
                        <record>
                            <UnitPrice>0</UnitPrice>
                        </record>
                        <record>
                            <UnitPrice>0</UnitPrice>
                        </record>
                        <record>
                            <UnitPrice>0</UnitPrice>
                        </record>
                        <record>
                            <UnitPrice>0</UnitPrice>
                        </record>
                    </TierServiceModePrices>
                </record>
                <record>
                    <HoseNumber>3</HoseNumber>
                    <Enabled>1</Enabled>
                    <ProductNumber>70000020</ProductNumber>
                    <PrimaryTank>3</PrimaryTank>
                    <SecondaryTank>0</SecondaryTank>
                    <PrimaryBlendPercentage>100</PrimaryBlendPercentage>
                    <TierServiceModePrices>
                        <record>
                            <UnitPrice>3000</UnitPrice>
                        </record>
                        <record>
                            <UnitPrice>0</UnitPrice>
                        </record>
                        <record>
                            <UnitPrice>3200</UnitPrice>
                        </record>
                        <record>
                            <UnitPrice>0</UnitPrice>
                        </record>
                        <record>
                            <UnitPrice>0</UnitPrice>
                        </record>
                        <record>
                            <UnitPrice>0</UnitPrice>
                        </record>
                        <record>
                            <UnitPrice>0</UnitPrice>
                        </record>
                        <record>
                            <UnitPrice>0</UnitPrice>
                        </record>
                        <record>
                            <UnitPrice>0</UnitPrice>
                        </record>
                        <record>
                            <UnitPrice>0</UnitPrice>
                        </record>
                    </TierServiceModePrices>
                </record>
                <record>
                    <HoseNumber>4</HoseNumber>
                    <Enabled>1</Enabled>
                    <ProductNumber>70000021</ProductNumber>
                    <PrimaryTank>4</PrimaryTank>
                    <SecondaryTank>0</SecondaryTank>
                    <PrimaryBlendPercentage>100</PrimaryBlendPercentage>
                    <TierServiceModePrices>
                        <record>
                            <UnitPrice>4000</UnitPrice>
                        </record>
                        <record>
                            <UnitPrice>0</UnitPrice>
                        </record>
                        <record>
                            <UnitPrice>4200</UnitPrice>
                        </record>
                        <record>
                            <UnitPrice>0</UnitPrice>
                        </record>
                        <record>
                            <UnitPrice>0</UnitPrice>
                        </record>
                        <record>
                            <UnitPrice>0</UnitPrice>
                        </record>
                        <record>
                            <UnitPrice>0</UnitPrice>
                        </record>
                        <record>
                            <UnitPrice>0</UnitPrice>
                        </record>
                        <record>
                            <UnitPrice>0</UnitPrice>
                        </record>
                        <record>
                            <UnitPrice>0</UnitPrice>
                        </record>
                    </TierServiceModePrices>
                </record>
            </HoseRecords>
        </record>
        <record>
            <FuelingPointNumber>3</FuelingPointNumber>
            <Enabled>1</Enabled>
            <DefaultTier>1</DefaultTier>
            <ServiceMode>1</ServiceMode>
            <VolumeMultiplier>1000</VolumeMultiplier>
            <PricePerUnitMultiplier>1000</PricePerUnitMultiplier>
            <MoneyMultiplier>100</MoneyMultiplier>
            <MaxAuthAmount>20000</MaxAuthAmount>
            <MaxAuthVolume>200000</MaxAuthVolume>
            <CallingAction>0</CallingAction>
            <NonIntegratedPump>0</NonIntegratedPump>
            <PumpPPUPrecision>3</PumpPPUPrecision>
            <PumpMoneyPrecision>2</PumpMoneyPrecision>
            <PumpVolumePrecision>3</PumpVolumePrecision>
            <MaxStack>2</MaxStack>
            <HoseRecords>
                <record>
                    <HoseNumber>1</HoseNumber>
                    <Enabled>1</Enabled>
                    <ProductNumber>70000019</ProductNumber>
                    <PrimaryTank>1</PrimaryTank>
                    <SecondaryTank>0</SecondaryTank>
                    <PrimaryBlendPercentage>100</PrimaryBlendPercentage>
                    <TierServiceModePrices>
                        <record>
                            <UnitPrice>1000</UnitPrice>
                        </record>
                        <record>
                            <UnitPrice>0</UnitPrice>
                        </record>
                        <record>
                            <UnitPrice>1200</UnitPrice>
                        </record>
                        <record>
                            <UnitPrice>0</UnitPrice>
                        </record>
                        <record>
                            <UnitPrice>0</UnitPrice>
                        </record>
                        <record>
                            <UnitPrice>0</UnitPrice>
                        </record>
                        <record>
                            <UnitPrice>0</UnitPrice>
                        </record>
                        <record>
                            <UnitPrice>0</UnitPrice>
                        </record>
                        <record>
                            <UnitPrice>0</UnitPrice>
                        </record>
                        <record>
                            <UnitPrice>0</UnitPrice>
                        </record>
                    </TierServiceModePrices>
                </record>
                <record>
                    <HoseNumber>2</HoseNumber>
                    <Enabled>1</Enabled>
                    <ProductNumber>70000022</ProductNumber>
                    <PrimaryTank>2</PrimaryTank>
                    <SecondaryTank>0</SecondaryTank>
                    <PrimaryBlendPercentage>100</PrimaryBlendPercentage>
                    <TierServiceModePrices>
                        <record>
                            <UnitPrice>2000</UnitPrice>
                        </record>
                        <record>
                            <UnitPrice>0</UnitPrice>
                        </record>
                        <record>
                            <UnitPrice>2200</UnitPrice>
                        </record>
                        <record>
                            <UnitPrice>0</UnitPrice>
                        </record>
                        <record>
                            <UnitPrice>0</UnitPrice>
                        </record>
                        <record>
                            <UnitPrice>0</UnitPrice>
                        </record>
                        <record>
                            <UnitPrice>0</UnitPrice>
                        </record>
                        <record>
                            <UnitPrice>0</UnitPrice>
                        </record>
                        <record>
                            <UnitPrice>0</UnitPrice>
                        </record>
                        <record>
                            <UnitPrice>0</UnitPrice>
                        </record>
                    </TierServiceModePrices>
                </record>
                <record>
                    <HoseNumber>3</HoseNumber>
                    <Enabled>1</Enabled>
                    <ProductNumber>70000020</ProductNumber>
                    <PrimaryTank>3</PrimaryTank>
                    <SecondaryTank>0</SecondaryTank>
                    <PrimaryBlendPercentage>100</PrimaryBlendPercentage>
                    <TierServiceModePrices>
                        <record>
                            <UnitPrice>3000</UnitPrice>
                        </record>
                        <record>
                            <UnitPrice>0</UnitPrice>
                        </record>
                        <record>
                            <UnitPrice>3200</UnitPrice>
                        </record>
                        <record>
                            <UnitPrice>0</UnitPrice>
                        </record>
                        <record>
                            <UnitPrice>0</UnitPrice>
                        </record>
                        <record>
                            <UnitPrice>0</UnitPrice>
                        </record>
                        <record>
                            <UnitPrice>0</UnitPrice>
                        </record>
                        <record>
                            <UnitPrice>0</UnitPrice>
                        </record>
                        <record>
                            <UnitPrice>0</UnitPrice>
                        </record>
                        <record>
                            <UnitPrice>0</UnitPrice>
                        </record>
                    </TierServiceModePrices>
                </record>
                <record>
                    <HoseNumber>4</HoseNumber>
                    <Enabled>1</Enabled>
                    <ProductNumber>70000021</ProductNumber>
                    <PrimaryTank>4</PrimaryTank>
                    <SecondaryTank>0</SecondaryTank>
                    <PrimaryBlendPercentage>100</PrimaryBlendPercentage>
                    <TierServiceModePrices>
                        <record>
                            <UnitPrice>4000</UnitPrice>
                        </record>
                        <record>
                            <UnitPrice>0</UnitPrice>
                        </record>
                        <record>
                            <UnitPrice>4200</UnitPrice>
                        </record>
                        <record>
                            <UnitPrice>0</UnitPrice>
                        </record>
                        <record>
                            <UnitPrice>0</UnitPrice>
                        </record>
                        <record>
                            <UnitPrice>0</UnitPrice>
                        </record>
                        <record>
                            <UnitPrice>0</UnitPrice>
                        </record>
                        <record>
                            <UnitPrice>0</UnitPrice>
                        </record>
                        <record>
                            <UnitPrice>0</UnitPrice>
                        </record>
                        <record>
                            <UnitPrice>0</UnitPrice>
                        </record>
                    </TierServiceModePrices>
                </record>
            </HoseRecords>
        </record>
        <record>
            <FuelingPointNumber>4</FuelingPointNumber>
            <Enabled>1</Enabled>
            <DefaultTier>1</DefaultTier>
            <ServiceMode>1</ServiceMode>
            <VolumeMultiplier>1000</VolumeMultiplier>
            <PricePerUnitMultiplier>1000</PricePerUnitMultiplier>
            <MoneyMultiplier>100</MoneyMultiplier>
            <MaxAuthAmount>20000</MaxAuthAmount>
            <MaxAuthVolume>200000</MaxAuthVolume>
            <CallingAction>0</CallingAction>
            <NonIntegratedPump>1</NonIntegratedPump>
            <PumpPPUPrecision>3</PumpPPUPrecision>
            <PumpMoneyPrecision>2</PumpMoneyPrecision>
            <PumpVolumePrecision>3</PumpVolumePrecision>
            <MaxStack>1</MaxStack>
            <HoseRecords>
                <record>
                    <HoseNumber>1</HoseNumber>
                    <Enabled>1</Enabled>
                    <ProductNumber>70000019</ProductNumber>
                    <PrimaryTank>1</PrimaryTank>
                    <SecondaryTank>0</SecondaryTank>
                    <PrimaryBlendPercentage>100</PrimaryBlendPercentage>
                    <TierServiceModePrices>
                        <record>
                            <UnitPrice>1000</UnitPrice>
                        </record>
                        <record>
                            <UnitPrice>0</UnitPrice>
                        </record>
                        <record>
                            <UnitPrice>1200</UnitPrice>
                        </record>
                        <record>
                            <UnitPrice>0</UnitPrice>
                        </record>
                        <record>
                            <UnitPrice>0</UnitPrice>
                        </record>
                        <record>
                            <UnitPrice>0</UnitPrice>
                        </record>
                        <record>
                            <UnitPrice>0</UnitPrice>
                        </record>
                        <record>
                            <UnitPrice>0</UnitPrice>
                        </record>
                        <record>
                            <UnitPrice>0</UnitPrice>
                        </record>
                        <record>
                            <UnitPrice>0</UnitPrice>
                        </record>
                    </TierServiceModePrices>
                </record>
                <record>
                    <HoseNumber>2</HoseNumber>
                    <Enabled>1</Enabled>
                    <ProductNumber>70000022</ProductNumber>
                    <PrimaryTank>2</PrimaryTank>
                    <SecondaryTank>0</SecondaryTank>
                    <PrimaryBlendPercentage>100</PrimaryBlendPercentage>
                    <TierServiceModePrices>
                        <record>
                            <UnitPrice>2000</UnitPrice>
                        </record>
                        <record>
                            <UnitPrice>0</UnitPrice>
                        </record>
                        <record>
                            <UnitPrice>2200</UnitPrice>
                        </record>
                        <record>
                            <UnitPrice>0</UnitPrice>
                        </record>
                        <record>
                            <UnitPrice>0</UnitPrice>
                        </record>
                        <record>
                            <UnitPrice>0</UnitPrice>
                        </record>
                        <record>
                            <UnitPrice>0</UnitPrice>
                        </record>
                        <record>
                            <UnitPrice>0</UnitPrice>
                        </record>
                        <record>
                            <UnitPrice>0</UnitPrice>
                        </record>
                        <record>
                            <UnitPrice>0</UnitPrice>
                        </record>
                    </TierServiceModePrices>
                </record>
                <record>
                    <HoseNumber>3</HoseNumber>
                    <Enabled>1</Enabled>
                    <ProductNumber>70000020</ProductNumber>
                    <PrimaryTank>3</PrimaryTank>
                    <SecondaryTank>0</SecondaryTank>
                    <PrimaryBlendPercentage>100</PrimaryBlendPercentage>
                    <TierServiceModePrices>
                        <record>
                            <UnitPrice>3000</UnitPrice>
                        </record>
                        <record>
                            <UnitPrice>0</UnitPrice>
                        </record>
                        <record>
                            <UnitPrice>3200</UnitPrice>
                        </record>
                        <record>
                            <UnitPrice>0</UnitPrice>
                        </record>
                        <record>
                            <UnitPrice>0</UnitPrice>
                        </record>
                        <record>
                            <UnitPrice>0</UnitPrice>
                        </record>
                        <record>
                            <UnitPrice>0</UnitPrice>
                        </record>
                        <record>
                            <UnitPrice>0</UnitPrice>
                        </record>
                        <record>
                            <UnitPrice>0</UnitPrice>
                        </record>
                        <record>
                            <UnitPrice>0</UnitPrice>
                        </record>
                    </TierServiceModePrices>
                </record>
                <record>
                    <HoseNumber>4</HoseNumber>
                    <Enabled>1</Enabled>
                    <ProductNumber>70000021</ProductNumber>
                    <PrimaryTank>4</PrimaryTank>
                    <SecondaryTank>0</SecondaryTank>
                    <PrimaryBlendPercentage>100</PrimaryBlendPercentage>
                    <TierServiceModePrices>
                        <record>
                            <UnitPrice>4000</UnitPrice>
                        </record>
                        <record>
                            <UnitPrice>0</UnitPrice>
                        </record>
                        <record>
                            <UnitPrice>4200</UnitPrice>
                        </record>
                        <record>
                            <UnitPrice>0</UnitPrice>
                        </record>
                        <record>
                            <UnitPrice>0</UnitPrice>
                        </record>
                        <record>
                            <UnitPrice>0</UnitPrice>
                        </record>
                        <record>
                            <UnitPrice>0</UnitPrice>
                        </record>
                        <record>
                            <UnitPrice>0</UnitPrice>
                        </record>
                        <record>
                            <UnitPrice>0</UnitPrice>
                        </record>
                        <record>
                            <UnitPrice>0</UnitPrice>
                        </record>
                    </TierServiceModePrices>
                </record>
            </HoseRecords>
        </record>
    </FuelingPointRecords>
</RelayFile>